itemshop
