Metadata-Version: 1.0
Name: flask-itemshop
Version: 0.2
Summary: 
